xDev/__init__.py
xDev/requirements.txt
xDev/xConan.py
xDev/xFrame.py
hg_xdev-0.36.dist-info/METADATA
hg_xdev-0.36.dist-info/WHEEL
hg_xdev-0.36.dist-info/top_level.txt
hg_xdev-0.36.dist-info/RECORD
