Metadata-Version: 2.1
Name: hg-xdev
Version: 0.36
Requires-Dist: conan
Requires-Dist: hg-xpy
